fantasy_agn/__init__.py
fantasy_agn/eigen/gal_eigenspec_Yip2004.fits
fantasy_agn/eigen/qso_eigenspec_Yip2004_global.fits
fantasy_agn/input/balmer.csv
fantasy_agn/input/broad.csv
fantasy_agn/input/coronal.csv
fantasy_agn/input/feII_forbidden.csv
fantasy_agn/input/feII_model.csv
fantasy_agn/input/feii_IZw1.csv
fantasy_agn/input/helium.csv
fantasy_agn/input/hydrogen.csv
fantasy_agn/input/narrow_basic.csv
fantasy_agn/input/narrow_plus.csv
fantasy_agn/input/oiii_nii.csv
fantasy_agn/input/uvfe.csv
fantasy_agn/models.py
fantasy_agn/sfddata/README.md
fantasy_agn/sfddata/SFD_dust_4096_ngp.fits
fantasy_agn/sfddata/SFD_dust_4096_sgp.fits
fantasy_agn/sfddata/SFD_mask_4096_ngp.fits
fantasy_agn/sfddata/SFD_mask_4096_sgp.fits
fantasy_agn/tools.py
fantasy_agn-1.0.0.dist-info/WHEEL
fantasy_agn-1.0.0.dist-info/METADATA
fantasy_agn-1.0.0.dist-info/RECORD
